mpyc-stubs/__init__.py
mpyc-stubs/_sectypes.py
mpyc-stubs/asyncoro.py
mpyc-stubs/asyncoro.pyi
mpyc-stubs/finfields.pyi
mpyc-stubs/gmpy.pyi
mpyc-stubs/py.typed
mpyc-stubs/runtime.pyi
mpyc-stubs/sectypes.pyi
mpyc-stubs/statistics.pyi
mpyc-stubs/thresha.pyi
mpyc-stubs/tests/__init__.py
mpyc-stubs/tests/test_complex_overloaded_annotations.py
mpyc-stubs/tests/test_covariant_annotations.py
tno/mpc/mpyc/stubs/__init__.py
tno/mpc/mpyc/stubs/_sectypes.py
tno/mpc/mpyc/stubs/asyncoro.py
tno/mpc/mpyc/stubs/asyncoro.pyi
tno/mpc/mpyc/stubs/finfields.pyi
tno/mpc/mpyc/stubs/gmpy.pyi
tno/mpc/mpyc/stubs/py.typed
tno/mpc/mpyc/stubs/runtime.pyi
tno/mpc/mpyc/stubs/sectypes.pyi
tno/mpc/mpyc/stubs/statistics.pyi
tno/mpc/mpyc/stubs/thresha.pyi
tno_mpc_mpyc_stubs-2.11.0.dist-info/LICENSE
tno_mpc_mpyc_stubs-2.11.0.dist-info/METADATA
tno_mpc_mpyc_stubs-2.11.0.dist-info/WHEEL
tno_mpc_mpyc_stubs-2.11.0.dist-info/top_level.txt
tno_mpc_mpyc_stubs-2.11.0.dist-info/RECORD
