Metadata-Version: 2.2
Name: tno.mpc.mpyc.stubs
Version: 2.11.0
Summary: Partial stubs for use with the MPyC library
Author-email: TNO PET Lab <petlab@tno.nl>
Maintainer-email: TNO PET Lab <petlab@tno.nl>
License: Apache License, Version 2.0
Project-URL: Homepage, https://pet.tno.nl/
Project-URL: Documentation, https://docs.pet.tno.nl/mpc/mpyc/stubs/2.11.0
Project-URL: Source, https://github.com/TNO-MPC/mpyc.stubs
Keywords: TNO,MPC,multi-party computation,MPyC,stubs
Platform: any
Classifier: License :: OSI Approved :: Apache Software License
Classifier: Programming Language :: Python :: 3
Classifier: Operating System :: OS Independent
Classifier: Intended Audience :: Developers
Classifier: Intended Audience :: Information Technology
Classifier: Intended Audience :: Science/Research
Classifier: Typing :: Typed
Requires-Python: >=3.9
License-File: LICENSE
Requires-Dist: mpyc~=0.10.0
Requires-Dist: typing_extensions; python_version < "3.11"
Provides-Extra: tests
Requires-Dist: numpy<3.0,>=1.0; extra == "tests"
Requires-Dist: pytest>=8.1; extra == "tests"
Requires-Dist: pytest-asyncio; extra == "tests"
